cl0l_minecraft_lib/__init__.py
cl0l_minecraft_lib/auth/__init__.py
cl0l_minecraft_lib/auth/microsoft.py
cl0l_minecraft_lib/auth/offline.py
cl0l_minecraft_lib/core/__init__.py
cl0l_minecraft_lib/core/assets.py
cl0l_minecraft_lib/core/downloader.py
cl0l_minecraft_lib/core/java.py
cl0l_minecraft_lib/core/launcher.py
cl0l_minecraft_lib/core/libraries.py
cl0l_minecraft_lib/core/manifest.py
cl0l_minecraft_lib/core/mods.py
cl0l_minecraft_lib/core/resolver.py
cl0l_minecraft_lib/models/__init__.py
cl0l_minecraft_lib/models/asset.py
cl0l_minecraft_lib/models/library.py
cl0l_minecraft_lib/models/version.py
cl0l_minecraft_lib/profiles/__init__.py
cl0l_minecraft_lib/profiles/fabric.py
cl0l_minecraft_lib/profiles/forge.py
cl0l_minecraft_lib/profiles/mods.py
cl0l_minecraft_lib/profiles/vanilla.py
cl0l_minecraft_lib-0.1.0.dist-info/METADATA
cl0l_minecraft_lib-0.1.0.dist-info/WHEEL
cl0l_minecraft_lib-0.1.0.dist-info/top_level.txt
cl0l_minecraft_lib-0.1.0.dist-info/RECORD
