Metadata-Version: 2.4
Name: cl0l_minecraft_lib
Version: 0.1.0
Summary: Minecraft launcher library with mod support.
Author-email: Александр <nnjscp@gmail.com>
License: MIT
Requires-Python: >=3.8
Requires-Dist: requests>=2.30
